Metadata-Version: 2.1
Name: lifesci
Version: 0.3.2
Summary: This repo contains python3 life sciences utilities.
Home-page: https://github.com/bmmalone/pylifesci
Author: Brandon Malone
Author-email: bmmalone@gmail.com
License: MIT
Keywords: bioinformatics utilities
Classifier: License :: OSI Approved :: MIT License
Classifier: Programming Language :: Python :: 3.9
License-File: LICENSE
Requires-Dist: biopython
Requires-Dist: goatools
Requires-Dist: joblib
Requires-Dist: mygene
Requires-Dist: numpy
Requires-Dist: matplotlib
Requires-Dist: mhcnames
Requires-Dist: pandas
Requires-Dist: pepdata
Requires-Dist: pillow
Requires-Dist: pyensembl
Requires-Dist: pyllars
Requires-Dist: pysam
Requires-Dist: sexpdata
Requires-Dist: tqdm
Requires-Dist: weblogo
Provides-Extra: dev
Requires-Dist: codecov (==2.1.12) ; extra == 'dev'
Requires-Dist: coverage (==6.5.0) ; extra == 'dev'
Requires-Dist: docutils (==0.19) ; extra == 'dev'
Requires-Dist: pylint (==2.15.5) ; extra == 'dev'
Requires-Dist: pytest-console-scripts (==1.3.1) ; extra == 'dev'
Requires-Dist: pytest-cov (==4.0.0) ; extra == 'dev'
Requires-Dist: pytest-datadir (==1.4.1) ; extra == 'dev'
Requires-Dist: pytest (==7.2.0) ; extra == 'dev'
Requires-Dist: setuptools-scm (==7.1.0) ; extra == 'dev'
Requires-Dist: sphinx-argparse (==0.3.2) ; extra == 'dev'
Requires-Dist: Sphinx (==6.1.3) ; extra == 'dev'
Requires-Dist: sphinx-rtd-theme ; extra == 'dev'
Requires-Dist: coveralls ; extra == 'dev'
Requires-Dist: pytest-runner ; extra == 'dev'
Requires-Dist: twine ; extra == 'dev'
Requires-Dist: readme-renderer[md] ; extra == 'dev'
